rtplot/client.py
rtplot/example_code.py
rtplot/plot_log.py
rtplot/saved_plots/.gitignore
rtplot/server.py
better_rtplot-0.1.7.dist-info/LICENSE
better_rtplot-0.1.7.dist-info/METADATA
better_rtplot-0.1.7.dist-info/WHEEL
better_rtplot-0.1.7.dist-info/RECORD
