Metadata-Version: 2.1
Name: better-rtplot
Version: 0.1.7
Summary: 
License: GPL V3.0
Author: jmontp
Author-email: jmontp@umich.edu
Requires-Python: >=3.9,<3.13
Classifier: License :: Other/Proprietary License
Classifier: Programming Language :: Python :: 3
Classifier: Programming Language :: Python :: 3.9
Classifier: Programming Language :: Python :: 3.10
Classifier: Programming Language :: Python :: 3.11
Provides-Extra: server
Requires-Dist: numpy (>=1.23.5)
Requires-Dist: pandas (>=1.5.3) ; extra == "server"
Requires-Dist: pyarrow (>=11.0.0) ; extra == "server"
Requires-Dist: pyqtgraph (>=0.13.0) ; extra == "server"
Requires-Dist: pyside6 (>6.4.0) ; extra == "server"
Requires-Dist: pyzmq (>=25.0.0)
